{"name":"drumbit","edition":"Free","options":{"volume":0.7,"tempo":110,"swing":0,"kit":"12","effect":{"id":0,"level":0},"compressor":{"bypass":1,"threshold":-20,"ratio":4,"attack":0.0010000000474974513,"release":0.25,"knee":5},"lowpass":{"bypass":1,"frequency":800,"q":1},"highpass":{"bypass":1,"frequency":800,"q":1}},"pattern1":{"track1":{"vol":1,"pan":1,"pitch":1,"steps":[0,0,0,0,0,0,0,0,0,0,0,0,0,0,0,0]},"track2":{"vol":1,"pan":1,"pitch":1,"steps":[0,0,0,0,0,0,0,0,0,0,0,0,0,0,0,0]},"track3":{"vol":1,"pan":1,"pitch":1,"steps":[0,0,0,0,0,0,0,0,0,0,0,0,0,0,0,0]},"track4":{"vol":1,"pan":1,"pitch":1,"steps":[0,0,0,0,0,0,0,0,0,0,0,0,0,0,0,0]},"track5":{"vol":1,"pan":1,"pitch":1,"steps":[0,0,0,0,0,0,0,0,0,0,0,0,0,0,0,0]},"track6":{"vol":1,"pan":40,"pitch":1,"steps":[1,0,1,0,1,0,1,0,1,0,1,0,1,0,1,0]},"track7":{"vol":1,"pan":-40,"pitch":1,"steps":[0,0,0,0,1,0,0,0,0,0,0,0,1,0,0,0]},"track8":{"vol":1,"pan":0,"pitch":1,"steps":[1,0,0,1,0,0,1,0,0,1,1,0,0,0,0,0]}},"pattern2":{"track1":{"vol":1,"pan":1,"pitch":1,"steps":[0,0,0,0,0,0,0,0,0,0,0,0,0,0,0,0]},"track2":{"vol":1,"pan":1,"pitch":1,"steps":[0,0,0,0,0,0,0,0,0,0,0,0,0,0,0,0]},"track3":{"vol":1,"pan":1,"pitch":1,"steps":[0,0,0,0,0,0,0,0,0,0,0,0,0,0,0,0]},"track4":{"vol":1,"pan":1,"pitch":1,"steps":[0,0,0,0,0,0,0,0,0,0,0,0,0,0,0,0]},"track5":{"vol":1,"pan":1,"pitch":1,"steps":[0,0,0,0,0,0,0,0,0,0,0,0,0,0,0,0]},"track6":{"vol":1,"pan":40,"pitch":1,"steps":[0,0,0,0,0,0,0,0,0,0,0,0,0,0,0,0]},"track7":{"vol":1,"pan":-40,"pitch":1,"steps":[0,0,0,0,0,0,0,0,0,0,0,0,0,0,0,0]},"track8":{"vol":1,"pan":0,"pitch":1,"steps":[0,0,0,0,0,0,0,0,0,0,0,0,0,0,0,0]}},"pattern3":{"track1":{"vol":1,"pan":1,"pitch":1,"steps":[0,0,0,0,0,0,0,0,0,0,0,0,0,0,0,0]},"track2":{"vol":1,"pan":1,"pitch":1,"steps":[0,0,0,0,0,0,0,0,0,0,0,0,0,0,0,0]},"track3":{"vol":1,"pan":1,"pitch":1,"steps":[0,0,0,0,0,0,0,0,0,0,0,0,0,0,0,0]},"track4":{"vol":1,"pan":1,"pitch":1,"steps":[0,0,0,0,0,0,0,0,0,0,0,0,0,0,0,0]},"track5":{"vol":1,"pan":1,"pitch":1,"steps":[0,0,0,0,0,0,0,0,0,0,0,0,0,0,0,0]},"track6":{"vol":1,"pan":40,"pitch":1,"steps":[0,0,0,0,0,0,0,0,0,0,0,0,0,0,0,0]},"track7":{"vol":1,"pan":-40,"pitch":1,"steps":[0,0,0,0,0,0,0,0,0,0,0,0,0,0,0,0]},"track8":{"vol":1,"pan":0,"pitch":1,"steps":[0,0,0,0,0,0,0,0,0,0,0,0,0,0,0,0]}},"pattern4":{"track1":{"vol":1,"pan":1,"pitch":1,"steps":[0,0,0,0,0,0,0,0,0,0,0,0,0,0,0,0]},"track2":{"vol":1,"pan":1,"pitch":1,"steps":[0,0,0,0,0,0,0,0,0,0,0,0,0,0,0,0]},"track3":{"vol":1,"pan":1,"pitch":1,"steps":[0,0,0,0,0,0,0,0,0,0,0,0,0,0,0,0]},"track4":{"vol":1,"pan":1,"pitch":1,"steps":[0,0,0,0,0,0,0,0,0,0,0,0,0,0,0,0]},"track5":{"vol":1,"pan":1,"pitch":1,"steps":[0,0,0,0,0,0,0,0,0,0,0,0,0,0,0,0]},"track6":{"vol":1,"pan":40,"pitch":1,"steps":[0,0,0,0,0,0,0,0,0,0,0,0,0,0,0,0]},"track7":{"vol":1,"pan":-40,"pitch":1,"steps":[0,0,0,0,0,0,0,0,0,0,0,0,0,0,0,0]},"track8":{"vol":1,"pan":0,"pitch":1,"steps":[0,0,0,0,0,0,0,0,0,0,0,0,0,0,0,0]}}}